{
    "1106": {
        "buses": [
            "Not Applicable"
        ], 
        "certified": "False", 
        "class_names": [
            "MultipleMotors"
        ], 
        "detail_url": "https://dsc-test.modelowanie.pl/resources/dsc/ds/1106/", 
        "development_status": "released", 
        "documentation": [
            {
                "documentation_type": "Generated", 
                "pk": 341, 
                "title": "PDF generated from POGO", 
                "updated_by_script": true, 
                "url": "http://www.esrf.eu/computing/cs/tango/tango_doc/ds_doc/tango-ds/Motion/MultipleMotors/MultipleMotors.pdf"
            }
        ], 
        "families": [
            "Motion"
        ], 
        "last_update": "2017-01-28 04:48:56.749804+00:00", 
        "last_update_method": "url", 
        "license": "None", 
        "manufacturers": [
            "none"
        ], 
        "name": "MultipleMotors", 
        "products": [
            ""
        ], 
        "repository_contact_email": "", 
        "repository_url": "http://svn.code.sf.net/p/tango-ds/code/DeviceClasses/Motion/MultipleMotors", 
        "status": "updated", 
        "tag": "Release_1_17", 
        "update_url": "https://dsc-test.modelowanie.pl/resources/dsc/ds/1106/update/", 
        "updated_by_script": true
    }
}