{
    "1217": {
        "buses": [
            "Data Socket"
        ], 
        "certified": "False", 
        "class_names": [
            "OxfCryostreamCooler"
        ], 
        "detail_url": "https://dsc-test.modelowanie.pl/resources/dsc/ds/1217/", 
        "development_status": "released", 
        "documentation": [
            {
                "documentation_type": "Generated", 
                "pk": 500, 
                "title": "PDF generated from POGO", 
                "updated_by_script": true, 
                "url": "http://www.esrf.eu/computing/cs/tango/tango_doc/ds_doc/tango-ds/Temperature/OxfCryostreamCooler/OxfCryostreamCooler.pdf"
            }
        ], 
        "families": [
            "Instrumentation"
        ], 
        "last_update": "2017-01-28 06:01:58.803206+00:00", 
        "last_update_method": "url", 
        "license": "None", 
        "manufacturers": [
            "Oxford Cryosystems"
        ], 
        "name": "OxfCryostreamCooler", 
        "products": [
            "700 Series Cryostream Cooler"
        ], 
        "repository_contact_email": "", 
        "repository_url": "http://svn.code.sf.net/p/tango-ds/code/DeviceClasses/Temperature/OxfCryostreamCooler", 
        "status": "updated", 
        "tag": "Release_1_1", 
        "update_url": "https://dsc-test.modelowanie.pl/resources/dsc/ds/1217/update/", 
        "updated_by_script": true
    }
}